aws_cdk_ssm_sdk_parameter/__init__.py
aws_cdk_ssm_sdk_parameter/py.typed
aws_cdk_ssm_sdk_parameter/_jsii/__init__.py
aws_cdk_ssm_sdk_parameter/_jsii/aws-cdk-ssm-sdk-parameter@0.0.9.jsii.tgz
aws_cdk_ssm_sdk_parameter-0.0.9.dist-info/METADATA
aws_cdk_ssm_sdk_parameter-0.0.9.dist-info/WHEEL
aws_cdk_ssm_sdk_parameter-0.0.9.dist-info/top_level.txt
aws_cdk_ssm_sdk_parameter-0.0.9.dist-info/RECORD
