Metadata-Version: 2.1
Name: aws-cdk-ssm-sdk-parameter
Version: 0.0.9
Summary: aws-cdk-ssm-sdk-parameter
Home-page: https://github.com/mmuller88/aws-cdk-ssm-sdk-parameter
Author: martin.mueller<damadden88@googlemail.de>
License: Apache-2.0
Project-URL: Source, https://github.com/mmuller88/aws-cdk-ssm-sdk-parameter
Platform: UNKNOWN
Classifier: Intended Audience :: Developers
Classifier: Operating System :: OS Independent
Classifier: Programming Language :: JavaScript
Classifier: Programming Language :: Python :: 3 :: Only
Classifier: Programming Language :: Python :: 3.6
Classifier: Programming Language :: Python :: 3.7
Classifier: Programming Language :: Python :: 3.8
Classifier: Programming Language :: Python :: 3.9
Classifier: Typing :: Typed
Classifier: Development Status :: 5 - Production/Stable
Classifier: License :: OSI Approved
Requires-Python: >=3.6
Requires-Dist: aws-cdk.aws-cloudformation (==1.80.0)
Requires-Dist: aws-cdk.aws-iam (==1.80.0)
Requires-Dist: aws-cdk.aws-lambda (==1.80.0)
Requires-Dist: aws-cdk.cloud-assembly-schema (==1.80.0)
Requires-Dist: aws-cdk.core (==1.80.0)
Requires-Dist: aws-cdk.custom-resources (==1.80.0)
Requires-Dist: constructs (<4.0.0,>=3.2.27)
Requires-Dist: jsii (<2.0.0,>=1.16.0)
Requires-Dist: publication (>=0.0.3)
